quantile_estimator/__init__.py
quantile_estimator/version.py
quantile_estimator-0.1.2.dist-info/LICENSE
quantile_estimator-0.1.2.dist-info/METADATA
quantile_estimator-0.1.2.dist-info/WHEEL
quantile_estimator-0.1.2.dist-info/top_level.txt
quantile_estimator-0.1.2.dist-info/RECORD
